cloudshell/__init__.py
cloudshell/shell/__init__.py
cloudshell/shell/core/__init__.py
cloudshell/shell/core/api_utils.py
cloudshell/shell/core/base_autoload_structure_generator.py
cloudshell/shell/core/context_utils.py
cloudshell/shell/core/driver_context.py
cloudshell/shell/core/driver_utils.py
cloudshell/shell/core/orchestration_save_restore.py
cloudshell/shell/core/resource_driver_interface.py
cloudshell/shell/core/interfaces/__init__.py
cloudshell/shell/core/interfaces/save_restore.py
cloudshell/shell/core/session/__init__.py
cloudshell/shell/core/session/cloudshell_session.py
cloudshell/shell/core/session/logging_session.py
cloudshell/shell/core/utils/__init__.py
cloudshell/shell/core/utils/execution_info.py
cloudshell/shell/core/utils/get_installed_packages.py
tests/__init__.py
tests/test_orch_save_restore.py
tests/interfaces/__init__.py
tests/interfaces/test_save_and_restore.py
tests/session/__init__.py
tests/session/test_cloudshell_session.py
tests/session/test_logging_session.py
tests/utils/__init__.py
tests/utils/test_api_utils.py
tests/utils/test_context_utils.py
tests/utils/test_get_execution_info.py
cloudshell_shell_core-6.0.2.dist-info/METADATA
cloudshell_shell_core-6.0.2.dist-info/WHEEL
cloudshell_shell_core-6.0.2.dist-info/top_level.txt
cloudshell_shell_core-6.0.2.dist-info/RECORD
